atlas4d/__init__.py
atlas4d/async_client.py
atlas4d/client.py
atlas4d-0.3.0.dist-info/METADATA
atlas4d-0.3.0.dist-info/WHEEL
atlas4d-0.3.0.dist-info/top_level.txt
atlas4d-0.3.0.dist-info/RECORD
