Metadata-Version: 2.4
Name: atlas4d
Version: 0.3.0
Summary: Python client for Atlas4D - Open 4D Spatiotemporal AI Platform
Author-email: Digicom Ltd <office@atlas4d.tech>
Maintainer-email: Cris Bez <office@atlas4d.tech>
License: Apache-2.0
Project-URL: Homepage, https://atlas4d.tech
Project-URL: Documentation, https://github.com/crisbez/atlas4d-base/tree/main/sdk/python
Project-URL: Repository, https://github.com/crisbez/atlas4d-base
Project-URL: Issues, https://github.com/crisbez/atlas4d-base/issues
Project-URL: Changelog, https://github.com/crisbez/atlas4d-base/blob/main/CHANGELOG.md
Keywords: atlas4d,spatiotemporal,geospatial,postgresql,postgis,timescaledb,pgvector,api-client
Classifier: Development Status :: 4 - Beta
Classifier: Intended Audience :: Developers
Classifier: License :: OSI Approved :: Apache Software License
Classifier: Operating System :: OS Independent
Classifier: Programming Language :: Python :: 3
Classifier: Programming Language :: Python :: 3.8
Classifier: Programming Language :: Python :: 3.9
Classifier: Programming Language :: Python :: 3.10
Classifier: Programming Language :: Python :: 3.11
Classifier: Programming Language :: Python :: 3.12
Classifier: Topic :: Database
Classifier: Topic :: Scientific/Engineering :: GIS
Classifier: Topic :: Software Development :: Libraries :: Python Modules
Requires-Python: >=3.8
Requires-Dist: requests>=2.25.0
